CHANGELOG.md
nialog/__init__.py
nialog/logger.py
nialog-0.0.2.dist-info/LICENSE.md
nialog-0.0.2.dist-info/WHEEL
nialog-0.0.2.dist-info/METADATA
nialog-0.0.2.dist-info/RECORD
